topmost/__init__.py
topmost/data/__init__.py
topmost/data/basic_dataset.py
topmost/data/crosslingual_dataset.py
topmost/data/download.py
topmost/data/download_20ng.py
topmost/data/dynamic_dataset.py
topmost/data/file_utils.py
topmost/eva/__init__.py
topmost/eva/build_hierarchy.py
topmost/eva/classification.py
topmost/eva/clustering.py
topmost/eva/hierarchy_quality.py
topmost/eva/topic_coherence.py
topmost/eva/topic_diversity.py
topmost/models/Encoder.py
topmost/models/__init__.py
topmost/models/basic/CombinedTM.py
topmost/models/basic/DecTM.py
topmost/models/basic/ETM.py
topmost/models/basic/ProdLDA.py
topmost/models/basic/__init__.py
topmost/models/basic/ECRTM/ECR.py
topmost/models/basic/ECRTM/ECRTM.py
topmost/models/basic/ECRTM/__init__.py
topmost/models/basic/NSTM/NSTM.py
topmost/models/basic/NSTM/__init__.py
topmost/models/basic/NSTM/auto_diff_sinkhorn.py
topmost/models/basic/TSCTM/TSC.py
topmost/models/basic/TSCTM/TSCTM.py
topmost/models/basic/TSCTM/TopicDistQuant.py
topmost/models/basic/TSCTM/__init__.py
topmost/models/crosslingual/NMTM.py
topmost/models/crosslingual/__init__.py
topmost/models/crosslingual/InfoCTM/InfoCTM.py
topmost/models/crosslingual/InfoCTM/TAMI.py
topmost/models/crosslingual/InfoCTM/__init__.py
topmost/models/dynamic/DETM.py
topmost/models/dynamic/__init__.py
topmost/models/dynamic/CFDTM/CFDTM.py
topmost/models/dynamic/CFDTM/ETC.py
topmost/models/dynamic/CFDTM/UWE.py
topmost/models/dynamic/CFDTM/__init__.py
topmost/models/hierarchical/ProGBN.py
topmost/models/hierarchical/__init__.py
topmost/models/hierarchical/HyperMiner/HyperMiner.py
topmost/models/hierarchical/HyperMiner/__init__.py
topmost/models/hierarchical/HyperMiner/manifolds/__init__.py
topmost/models/hierarchical/HyperMiner/manifolds/base.py
topmost/models/hierarchical/HyperMiner/manifolds/euclidean.py
topmost/models/hierarchical/HyperMiner/manifolds/math_util.py
topmost/models/hierarchical/HyperMiner/manifolds/poincare.py
topmost/models/hierarchical/SawETM/SawETM.py
topmost-1.0.2.dist-info/LICENSE
topmost-1.0.2.dist-info/METADATA
topmost-1.0.2.dist-info/WHEEL
topmost-1.0.2.dist-info/top_level.txt
topmost-1.0.2.dist-info/RECORD
