Metadata-Version: 2.2
Name: topmost
Version: 1.0.2
Summary: Topmost: A Topic Modeling System Toolkit
Author-email: Xiaobao Wu <xiaobao002@e.ntu.edu.sg>
License: Apache 2.0 License
Project-URL: Documentation, https://topmost.readthedocs.io/en/latest/?badge=latest
Project-URL: Homepage, https://github.com/bobxwu/topmost
Project-URL: Repository, https://github.com/bobxwu/TopMost.git
Project-URL: Issues, https://github.com/bobxwu/TopMost/issues
Keywords: toolkit,topic model,neural topic model,bert,semantics,text
Requires-Python: >=3.9
License-File: LICENSE
Requires-Dist: pandas>=2.2.0
Requires-Dist: plotly>=6.0.0
Requires-Dist: sentence-transformers>=3.4.0
Requires-Dist: torchvision>=0.21.0
Requires-Dist: gensim>=4.3.3
Requires-Dist: scikit-learn>=1.6.1
Requires-Dist: tqdm>=4.66.0
Requires-Dist: fastopic>=1.0.0
Provides-Extra: dev
Requires-Dist: bertopic>=0.16.0; extra == "dev"
Provides-Extra: test
Requires-Dist: pytest>=8.3.0; extra == "test"
